README.md
package_info.json
setup.py
th2_grpc_crawler_data_service/__init__.py
th2_grpc_crawler_data_service/crawler_data_service.proto
th2_grpc_crawler_data_service/crawler_data_service_pb2.py
th2_grpc_crawler_data_service/crawler_data_service_pb2_grpc.py
th2_grpc_crawler_data_service/data_service_service.py
th2_grpc_crawler_data_service.egg-info/PKG-INFO
th2_grpc_crawler_data_service.egg-info/SOURCES.txt
th2_grpc_crawler_data_service.egg-info/dependency_links.txt
th2_grpc_crawler_data_service.egg-info/requires.txt
th2_grpc_crawler_data_service.egg-info/top_level.txt